<?xml version="1.0" encoding="UTF-8"?>
<ti:app xmlns:ti="http://ti.appcelerator.org">
    <property name="acs-oauth-secret-production" type="string">vhmWRd0za19txLtA2jnHSKjnR1C14fg8</property>
    <property name="acs-oauth-key-production" type="string">DagJQgT2xsfxMK46JVHooBjJ96TcedKr</property>
    <property name="acs-api-key-production" type="string">sCjZw79ku0T7Bz2ZTIcsblauHUGdP3JZ</property>
    <property name="acs-oauth-secret-development" type="string">fO8E4ZWrZ1CsVgbaRMOV5Fy25KsLUQg9</property>
    <property name="acs-oauth-key-development" type="string">tye5TqWmxOrOuyP76IMwUk8LiycBorkk</property>
    <property name="acs-api-key-development" type="string">LwBtvPJzalWh9Pfbr6u5XO7GrtdBH3HV</property>
    <id>com.netsmartcompany.xControl</id>
    <name>xControl</name>
    <version>1.0.4</version>
    <publisher>Netsmart LLC</publisher>
    <url>http://www.netmsartcompany.com</url>
    <description>Easily control your Insteon devices</description>
    <copyright>2013 by Netsmart LLC</copyright>
    <icon>icon72.png</icon>
    <persistent-wifi>false</persistent-wifi>
    <prerendered-icon>false</prerendered-icon>
    <statusbar-style>default</statusbar-style>
    <statusbar-hidden>false</statusbar-hidden>
    <fullscreen>false</fullscreen>
    <navbar-hidden>true</navbar-hidden>
    <analytics>true</analytics>
    <guid>96c328a6-f97d-45e0-8b7f-8ba2f81b0428</guid>
    <property name="ti.ui.defaultunit" type="string">system</property>
    <iphone>
        <orientations device="iphone">
            <orientation>Ti.UI.PORTRAIT</orientation>
        </orientations>
        <orientations device="ipad">
            <orientation>Ti.UI.PORTRAIT</orientation>
            <orientation>Ti.UI.UPSIDE_PORTRAIT</orientation>
            <orientation>Ti.UI.LANDSCAPE_LEFT</orientation>
            <orientation>Ti.UI.LANDSCAPE_RIGHT</orientation>
        </orientations>
    </iphone>
    <android xmlns:android="http://schemas.android.com/apk/res/android">
        <manifest android:versionCode="4" android:versionName="1.0.4"/>
    </android>
    <mobileweb>
        <precache/>
        <splash>
            <enabled>true</enabled>
            <inline-css-images>true</inline-css-images>
        </splash>
        <theme>default</theme>
    </mobileweb>
    <modules/>
    <deployment-targets>
        <target device="tizen">false</target>
        <target device="blackberry">false</target>
        <target device="android">true</target>
        <target device="ipad">true</target>
        <target device="iphone">true</target>
        <target device="mobileweb">false</target>
    </deployment-targets>
    <sdk-version>3.2.0.GA</sdk-version>
</ti:app>
